odoo/addons/product_readonly_security/README.rst
odoo/addons/product_readonly_security/__init__.py
odoo/addons/product_readonly_security/__manifest__.py
odoo/addons/product_readonly_security/i18n/es.po
odoo/addons/product_readonly_security/i18n/it.po
odoo/addons/product_readonly_security/i18n/product_readonly_security.pot
odoo/addons/product_readonly_security/models/__init__.py
odoo/addons/product_readonly_security/models/product_product.py
odoo/addons/product_readonly_security/models/product_readonly_security_mixin.py
odoo/addons/product_readonly_security/models/product_template.py
odoo/addons/product_readonly_security/readme/CONTRIBUTORS.md
odoo/addons/product_readonly_security/readme/DESCRIPTION.md
odoo/addons/product_readonly_security/readme/USAGE.md
odoo/addons/product_readonly_security/security/product_readonly_security.xml
odoo/addons/product_readonly_security/static/description/icon.png
odoo/addons/product_readonly_security/static/description/index.html
odoo/addons/product_readonly_security/tests/__init__.py
odoo/addons/product_readonly_security/tests/test_product_readonly_security.py
odoo_addon_product_readonly_security-17.0.1.0.0.5.dist-info/METADATA
odoo_addon_product_readonly_security-17.0.1.0.0.5.dist-info/WHEEL
odoo_addon_product_readonly_security-17.0.1.0.0.5.dist-info/top_level.txt
odoo_addon_product_readonly_security-17.0.1.0.0.5.dist-info/RECORD
